README.md
setup.py
pystork/__init__.py
pystork/activations.py
pystork/helpers.py
pystork/initializers.py
pystork/layer.py
pystork/layer_cache.py
pystork/model.py
pystork.egg-info/PKG-INFO
pystork.egg-info/SOURCES.txt
pystork.egg-info/dependency_links.txt
pystork.egg-info/top_level.txt
pystork/costs/__init__.py
pystork/costs/abstract_cost.py
pystork/costs/binary_classfication.py
pystork/data_generators/__init__.py
pystork/data_generators/threshold_data.py
pystork/optimizers/__init__.py
pystork/optimizers/abstract_optimizer.py
pystork/optimizers/gradient_descent.py
tests/__init__.py
tests/conftest.py
tests/test_activations.py
tests/test_costs.py
tests/test_data_generators.py
tests/test_helpers.py
tests/test_initializers.py
tests/test_layer.py
tests/test_model.py
tests/optimizers/__init__.py
tests/optimizers/test_gradient_descent.py