Metadata-Version: 1.0
Name: pystork
Version: 0.0.0
Summary: Deep learning library for academic use.
Home-page: https://github.com/yassineameur/pystork
Author: Yassine Ameur
Author-email: yassine.ameur2013@gmail.com
License: MIT
Platform: UNKNOWN
